rio_viz/__init__.py
rio_viz/app.py
rio_viz/io/__init__.py
rio_viz/io/mosaic.py
rio_viz/io/reader.py
rio_viz/resources/__init__.py
rio_viz/resources/enums.py
rio_viz/scripts/__init__.py
rio_viz/scripts/cli.py
rio_viz/templates/assets.html
rio_viz/templates/bands.html
rio_viz/templates/index.html
rio_viz/templates/map.html
rio_viz/templates/wmts.xml
rio_viz-0.14.0.dist-info/METADATA
rio_viz-0.14.0.dist-info/WHEEL
rio_viz-0.14.0.dist-info/entry_points.txt
rio_viz-0.14.0.dist-info/licenses/LICENSE
rio_viz-0.14.0.dist-info/RECORD
