Metadata-Version: 2.4
Name: rio-viz
Version: 0.14.0
Summary: Visualize Cloud Optimized GeoTIFF in browser
Project-URL: Source, https://github.com/developmentseed/rio-viz
Author-email: Vincent Sarago <vincent@developmentseed.com>
License: MIT License
License-File: LICENSE
Classifier: Intended Audience :: Information Technology
Classifier: Intended Audience :: Science/Research
Classifier: License :: OSI Approved :: BSD License
Classifier: Programming Language :: Python :: 3.9
Classifier: Programming Language :: Python :: 3.10
Classifier: Programming Language :: Python :: 3.11
Classifier: Programming Language :: Python :: 3.12
Classifier: Programming Language :: Python :: 3.13
Classifier: Topic :: Scientific/Engineering :: GIS
Requires-Python: >=3.9
Requires-Dist: braceexpand
Requires-Dist: rio-cogeo>=5.0
Requires-Dist: server-thread>=0.2.0
Requires-Dist: starlette-cramjam<0.5,>=0.4
Requires-Dist: titiler-core<0.22,>=0.20.0
Requires-Dist: uvicorn
Provides-Extra: dev
Requires-Dist: pre-commit; extra == 'dev'
Provides-Extra: mvt
Requires-Dist: rio-tiler-mvt<0.3,>=0.2; extra == 'mvt'
Provides-Extra: test
Requires-Dist: pytest; extra == 'test'
Requires-Dist: pytest-asyncio; extra == 'test'
Requires-Dist: pytest-cov; extra == 'test'
Requires-Dist: requests; extra == 'test'
